nastya_sort/__init__.py
nastya_sort/cli.py
nastya_sort_lnu-0.2.6.dist-info/METADATA
nastya_sort_lnu-0.2.6.dist-info/WHEEL
nastya_sort_lnu-0.2.6.dist-info/entry_points.txt
nastya_sort_lnu-0.2.6.dist-info/top_level.txt
nastya_sort_lnu-0.2.6.dist-info/RECORD
