Metadata-Version: 2.4
Name: nastya-sort-lnu
Version: 0.2.6
Summary: Simple sort utility implemented in Python with Click
Home-page: https://github.com/Nastia2004/nastya-sort-lnu
Author: Nastya
Author-email: nastavasilik1@gmail.com
Keywords: sort cli utility unix
Classifier: Programming Language :: Python :: 3
Classifier: Programming Language :: Python :: 3.8
Classifier: Programming Language :: Python :: 3.9
Classifier: Programming Language :: Python :: 3.10
Classifier: Programming Language :: Python :: 3.11
Classifier: License :: OSI Approved :: MIT License
Classifier: Operating System :: OS Independent
Classifier: Environment :: Console
Classifier: Topic :: Utilities
Requires-Python: >=3.8
Requires-Dist: click>=8.0
Dynamic: author
Dynamic: author-email
Dynamic: classifier
Dynamic: description
Dynamic: description-content-type
Dynamic: home-page
Dynamic: keywords
Dynamic: requires-dist
Dynamic: requires-python
Dynamic: summary
